oxi/__init__.py
oxi/__main__.py
oxi/activate_this.py
oxi/app.py
oxi/config.py
oxi/mp4parser.py
oxi/server.py
oxi/template.py
oxi/utils.py
oxi/websocket.py
oxi/examples/__init__.py
oxi/examples/activate_this.py
oxi/examples/run_main.py
oxi/tests/__init__.py
oxi/tests/activate_this.py
oxi/tests/first.py
oxi/tests/fsmon.py
oxi/tests/no_ctrl_c.py
oxi/tests/response.py
oxi/tests/second.py
oxi-0.2.35.dist-info/LICENSE
oxi-0.2.35.dist-info/METADATA
oxi-0.2.35.dist-info/WHEEL
oxi-0.2.35.dist-info/entry_points.txt
oxi-0.2.35.dist-info/top_level.txt
oxi-0.2.35.dist-info/RECORD
