Metadata-Version: 2.1
Name: oxi
Version: 0.2.35
Summary: ASGI full stack: Web Server, Web App and a ton of goodies.
Home-page: https://github.com/sandy98/oxi
Author: Domingo E. Savoretti
Author-email: esavoretti@gmail.com
License: MIT
Platform: UNKNOWN
Classifier: Programming Language :: Python :: 3
Classifier: License :: OSI Approved :: MIT License
Classifier: Operating System :: OS Independent
Requires-Python: >=3.9
License-File: LICENSE
